{
  "name": "5dim-taiwanese",
  "version": "0.16.1",
  "title": "5dim's Addons-Taiwanese locale",
  "author": "ajosak",
  "contact": "ajosak@skycg.info",
  "factorio_version": "0.16",
  "date": "2018-04-02",
  "description": "5dim's Modules Translation for Taiwanese.",
  "dependencies": [
      "? 5dim_transport",
      "? 5dim_trade",
      "? 5dim_resources",
      "? 5dim_ores",
      "? 5dim_mining",
      "? 5dim_nuclear",
      "? 5dim_module",
      "? 5dim_energy",
      "? 5dim_infiniteresearch",
      "? 5dim_equipment",
      "? 5dim_decoration",
      "? 5dim_botrecaller",
      "? 5dim_automatization",
      "? 5dim_autofill",
      "? 5dim_trains"
  ]
}
